sea_starterkit/__init__.py
sea_starterkit/__main__.py
sea_starterkit/sectionproperties_test.py
sea_starterkit/streamlit_test.py
sea_starterkit-0.2.0.dist-info/entry_points.txt
sea_starterkit-0.2.0.dist-info/LICENSE
sea_starterkit-0.2.0.dist-info/WHEEL
sea_starterkit-0.2.0.dist-info/METADATA
sea_starterkit-0.2.0.dist-info/RECORD
